{"Title":"Pete: Part 2","Year":"1999","Rated":"N/A","Released":"N/A","Season":"N/A","Episode":"N/A","Runtime":"N/A","Genre":"Comedy, Sci-Fi","Director":"Ed Bye","Writer":"Rob Grant, Doug Naylor","Actors":"Chris Barrie, Craig Charles, Danny John-Jules, Robert Llewellyn","Plot":"Kryten has accidentally turned Birdman's pet bird 'Pete' into a T-Rex which has gone on a rampage on-board Red Dwarf...","Language":"N/A","Country":"N/A","Awards":"N/A","Poster":"http://ia.media-imdb.com/images/M/MV5BMTMwNTIzMjczMV5BMl5BanBnXkFtZTcwNzU5MTI2MQ@@._V1_SX300.jpg","Metascore":"N/A","imdbRating":"7.1","imdbVotes":"93","imdbID":"tt0684171","seriesID":"N/A","Type":"episode","tomatoMeter":"N/A","tomatoImage":"N/A","tomatoRating":"N/A","tomatoReviews":"N/A","tomatoFresh":"N/A","tomatoRotten":"N/A","tomatoConsensus":"N/A","tomatoUserMeter":"N/A","tomatoUserRating":"N/A","tomatoUserReviews":"N/A","tomatoURL":"N/A","DVD":"N/A","BoxOffice":"N/A","Production":"N/A","Website":"N/A","Response":"True"}
